{"playlist":{"2":[{"thumbnail":"https://i.ytimg.com/vi/Yw6u6YkTgQ4/hq720.jpg","title":"hello world","creator":"Louie Zong","url":"https://youtube.com/watch?v=Yw6u6YkTgQ4"}],"test":[{"thumbnail":"https://i.ytimg.com/vi/5DEdR5lqnDE/hq720.jpg","title":"Funny 2 second video","creator":"Caid Schroeder","url":"https://youtube.com/watch?v=5DEdR5lqnDE"},{"thumbnail":"https://i.ytimg.com/vi/TK4N5W22Gts/hqdefault.jpg","title":"2 Second Video","creator":"Zetzu500","url":"https://youtube.com/watch?v=TK4N5W22Gts"},{"thumbnail":"https://i.ytimg.com/vi/MfSE956GpUE/hq720.jpg","title":"The Apothecary Diaries OP/Opening  - Hana ni Natte","creator":"AniClipsCollection","url":"https://youtube.com/watch?v=MfSE956GpUE"}]},"queque":[{"thumbnail":"https://i.ytimg.com/vi/TK4N5W22Gts/hqdefault.jpg","title":"2 Second Video","creator":"Zetzu500","url":"https://youtube.com/watch?v=TK4N5W22Gts"},{"thumbnail":"https://i.ytimg.com/vi/5DEdR5lqnDE/hq720.jpg","title":"Funny 2 second video","creator":"Caid Schroeder","url":"https://youtube.com/watch?v=5DEdR5lqnDE"},{"thumbnail":"https://i.ytimg.com/vi/MfSE956GpUE/hq720.jpg","title":"The Apothecary Diaries OP/Opening  - Hana ni Natte","creator":"AniClipsCollection","url":"https://youtube.com/watch?v=MfSE956GpUE"},{"thumbnail":"https://i.ytimg.com/vi/Yw6u6YkTgQ4/hq720.jpg","title":"hello world","creator":"Louie Zong","url":"https://youtube.com/watch?v=Yw6u6YkTgQ4"}]}